README.md
setup.cfg
setup.py
bin/kachery-cat
bin/kachery-client
bin/kachery-config-ephemeral-node
bin/kachery-generate-node-id
bin/kachery-info
bin/kachery-link
bin/kachery-load
bin/kachery-store
kachery_client/__init__.py
kachery_client/_daemon_connection.py
kachery_client/_exceptions.py
kachery_client/_feeds.py
kachery_client/_load_file.py
kachery_client/_local_kachery_storage.py
kachery_client/_misc.py
kachery_client/_mutables.py
kachery_client/_preventkeyboardinterrupt.py
kachery_client/_safe_pickle.py
kachery_client/_shellscript.py
kachery_client/_store_file.py
kachery_client/_temporarydirectory.py
kachery_client/_uri_handling.py
kachery_client/cli.py
kachery_client/enable_ephemeral.py
kachery_client/main.py
kachery_client/request_task.py
kachery_client/setup_colab_ephemeral.py
kachery_client/upload_file.py
kachery_client/version.py
kachery_client.egg-info/PKG-INFO
kachery_client.egg-info/SOURCES.txt
kachery_client.egg-info/dependency_links.txt
kachery_client.egg-info/requires.txt
kachery_client.egg-info/top_level.txt
kachery_client/direct_client/DirectClient.py
kachery_client/direct_client/__init__.py
kachery_client/ephemeral/__init__.py
kachery_client/ephemeral/config_ephemeral_node.py
kachery_client/ephemeral/ephemeral_load_file.py
kachery_client/ephemeral/ephemeral_upload_file.py
kachery_client/ephemeral_client_deprecated/EphemeralClient.py
kachery_client/ephemeral_client_deprecated/__init__.py
kachery_client/task_backend/RegisteredTaskFunction.py
kachery_client/task_backend/RequestedTask.py
kachery_client/task_backend/TaskBackend.py
kachery_client/task_backend/TaskJobManager.py
kachery_client/task_backend/__init__.py
kachery_client/task_backend/_old_register_task_functions.py
kachery_client/task_backend/_run_task.py
kachery_client/task_backend/_run_task_backend_worker.py
kachery_client/task_backend/_update_task_status.py
kachery_client/task_backend/run_task_backend.py
kachery_client/task_backend/taskfunction.py