Metadata-Version: 1.2
Name: kachery-client
Version: 1.1.7
Summary: Python client for kachery
Home-page: https://github.com/kacheryhub/kachery-client
Author: Jeremy Magland
Author-email: jmagland@flatironinstitute.org
License: UNKNOWN
Project-URL: Bug Tracker, https://github.com/kacheryhub/kachery-client/issues
Platform: UNKNOWN
Classifier: Programming Language :: Python :: 3
Classifier: License :: OSI Approved :: Apache Software License
Classifier: Operating System :: OS Independent
